ccf_spark
