Metadata-Version: 2.1
Name: ccf-spark
Version: 0.3.1
Summary: A little CCF implementation in a Spark context with networkx
Home-page: https://github.com/ErnestBidouille/ccf-spark
Author: Théo Chennebault
Author-email: theo.chennebault@le-cab-politique.fr
License: MIT
Platform: UNKNOWN
